fhnw_ds_weatherstation_client/__init__.py
fhnw_ds_weatherstation_client-0.0.19.dist-info/LICENSE
fhnw_ds_weatherstation_client-0.0.19.dist-info/METADATA
fhnw_ds_weatherstation_client-0.0.19.dist-info/WHEEL
fhnw_ds_weatherstation_client-0.0.19.dist-info/top_level.txt
fhnw_ds_weatherstation_client-0.0.19.dist-info/RECORD
