Metadata-Version: 2.1
Name: fhnw-ds-weatherstation-client
Version: 0.0.19
Summary: Provides access to the Wasserschutzpolizei Zurich live and historic weather data.
Home-page: https://github.com/jelleschutter/fhnw-ds-weatherstation-client
Author: Jelle Schutter
Author-email: jelle@schutter.xyz
License: UNKNOWN
Platform: UNKNOWN
Classifier: Programming Language :: Python :: 3
Classifier: License :: OSI Approved :: MIT License
Classifier: Operating System :: OS Independent
Requires-Python: >=3.7
Requires-Dist: pandas (>=1)
Requires-Dist: influxdb
Requires-Dist: requests
Requires-Dist: numpy
